Word_Count/__init__.py
Word_Count/count.py
Word_Count/word_count.py
Word_Count/tests/__init__.py
Word_Count/tests/test.py
Word_Counting_Luminoso2021-0.0.1.dist-info/METADATA
Word_Counting_Luminoso2021-0.0.1.dist-info/WHEEL
Word_Counting_Luminoso2021-0.0.1.dist-info/top_level.txt
Word_Counting_Luminoso2021-0.0.1.dist-info/RECORD
