Metadata-Version: 2.1
Name: Word-Counting-Luminoso2021
Version: 0.0.1
Summary: Basic Word Counting Package
Home-page: UNKNOWN
Author: NeuralNine (Florian Dedov)
Author-email: <mail@neuralnine.com>
License: UNKNOWN
Keywords: python,word counting
Platform: UNKNOWN
Classifier: Development Status :: 1 - Planning
Classifier: Intended Audience :: Developers
Classifier: Programming Language :: Python :: 3
Classifier: Operating System :: Unix
Classifier: Operating System :: MacOS :: MacOS X
Classifier: Operating System :: Microsoft :: Windows
Requires-Dist: pytest
Requires-Dist: collections
Requires-Dist: json
Requires-Dist: sys
Requires-Dist: os
Requires-Dist: inspect
